metrics/__init__.py
metrics/classification.py
metrics/image_quality.py
metrics/utils.py
tests/__init__.py
tests/test_classification.py
tests/test_gan_metrics.py
tests/test_image_quality.py
mmetrics-1.1.0.dist-info/METADATA
mmetrics-1.1.0.dist-info/WHEEL
mmetrics-1.1.0.dist-info/top_level.txt
mmetrics-1.1.0.dist-info/RECORD
