Metadata-Version: 2.1
Name: mmetrics
Version: 1.1.0
Summary: A library to perform image quality and classification assessment.
Author: Angie Carrillo
Author-email: a.carrillo@stariongroup.eu
Classifier: Programming Language :: Python :: 3
Classifier: License :: OSI Approved :: MIT License
Classifier: Operating System :: OS Independent
Requires-Python: >=3.12
Requires-Dist: numpy
Requires-Dist: scikit-image
Requires-Dist: scikit-learn
Requires-Dist: pytorch-fid
Requires-Dist: torch
